LICENSE
MANIFEST.in
README.md
flask_multiconfig.py
setup.cfg
setup.py
test_config.yml
tests.py
flask_multiconfig.egg-info/PKG-INFO
flask_multiconfig.egg-info/SOURCES.txt
flask_multiconfig.egg-info/dependency_links.txt
flask_multiconfig.egg-info/not-zip-safe
flask_multiconfig.egg-info/requires.txt
flask_multiconfig.egg-info/top_level.txt