Metadata-Version: 1.1
Name: flask-multiconfig
Version: 0.1
Summary: A simple extension to add advanced configuration source support.
Home-page: http://github.com/petermelias/flask-multiconfig
Author: Peter M. Elias
Author-email: petermelias@gmail.com
License: BSD
Platform: any
Classifier: Environment :: Web Environment
Classifier: Intended Audience :: Developers
Classifier: License :: OSI Approved :: BSD License
Classifier: Operating System :: OS Independent
Classifier: Programming Language :: Python
Classifier: Topic :: Internet :: WWW/HTTP :: Dynamic Content
Classifier: Topic :: Software Development :: Libraries :: Python Modules
